textual_pyfiglet_demo/__init__.py
textual_pyfiglet_demo/__main__.py
textual_pyfiglet_demo/styles.tcss
textual_pyfiglet_demo-0.1.0.dist-info/METADATA
textual_pyfiglet_demo-0.1.0.dist-info/WHEEL
textual_pyfiglet_demo-0.1.0.dist-info/entry_points.txt
textual_pyfiglet_demo-0.1.0.dist-info/RECORD
