Metadata-Version: 2.1
Name: textual-pyfiglet-demo
Version: 0.1.0
Summary: Small demo proposal of integrating PyFiglet with Textual
License: MIT
Author: edward-jazzhands
Author-email: ed.jazzhands@gmail.com
Requires-Python: >=3.10,<4.0
Classifier: License :: OSI Approved :: MIT License
Classifier: Programming Language :: Python :: 3
Classifier: Programming Language :: Python :: 3.10
Classifier: Programming Language :: Python :: 3.11
Classifier: Programming Language :: Python :: 3.12
Requires-Dist: pyfiglet (>=1.0.2,<2.0.0)
Requires-Dist: textual (>=0.83.0,<0.84.0)
